mcp_server_max/__init__.py
mcp_server_max/client.py
mcp_server_max/exchange.py
mcp_server_max/py.typed
mcp_server_max/server.py
mcp_server_max/types/__init__.py
mcp_server_max/types/account.py
mcp_server_max/types/currency.py
mcp_server_max/types/market.py
mcp_server_max/types/order.py
mcp_server_max/types/ticker.py
mcp_server_max-0.4.2.dist-info/METADATA
mcp_server_max-0.4.2.dist-info/WHEEL
mcp_server_max-0.4.2.dist-info/entry_points.txt
mcp_server_max-0.4.2.dist-info/licenses/LICENSE
mcp_server_max-0.4.2.dist-info/RECORD
